MANIFEST.in
README.md
setup.py
vaip/__init__.py
vaip/cli.py
vaip/constants.py
vaip/model_builder.py
vaip/model_deployer.py
vaip.egg-info/PKG-INFO
vaip.egg-info/SOURCES.txt
vaip.egg-info/dependency_links.txt
vaip.egg-info/entry_points.txt
vaip.egg-info/requires.txt
vaip.egg-info/top_level.txt
vaip/container/Dockerfile
vaip/container/__init__.py
vaip/container/app.py
vaip/container/prediction.py
vaip/container/requirements.txt