Metadata-Version: 1.0
Name: vaip
Version: 3.1
Summary: GCP Vertex AI Prediction high level SDK
Home-page: http://pypi.python.org/pypi/nmp/
Author: Viacheslav Kovalevskyi
Author-email: viacheslav@kovalevskyi.com
License: LICENSE
Platform: UNKNOWN
